checkers/__init__.py
checkers/__main__.py
checkers/checks.py
checkers/cli.py
checkers/collectors.py
checkers/config.py
checkers/contracts.py
checkers/core.py
checkers/exceptions.py
checkers/generators.py
checkers/printer.py
checkers/runner.py
checkers/summarizer.py
checkers/clients/api_client.py
checkers_cli-0.0.7.dist-info/METADATA
checkers_cli-0.0.7.dist-info/WHEEL
checkers_cli-0.0.7.dist-info/entry_points.txt
checkers_cli-0.0.7.dist-info/top_level.txt
checkers_cli-0.0.7.dist-info/RECORD
