Metadata-Version: 2.1
Name: checkers-cli
Version: 0.0.7
Summary: An extensible linter for dbt
Author-email: Tom Waterman <tjwaterman99@gmail.com>
Requires-Dist: pydantic <3.0
Requires-Dist: click <9.0
Requires-Dist: rich <14.0
Requires-Dist: toml <1.0
